Metadata-Version: 1.1
Name: yali-server
Version: 1.6.5
Summary: this is for log record for ios or android
Home-page: https://github.com/wenyali/yali_server.git
Author: wenyali
Author-email: 2917073217@qq.com
License: UNKNOWN
Keywords: keyword
Platform: UNKNOWN
Classifier: License :: OSI Approved :: MIT License
Classifier: Programming Language :: Python
Classifier: Intended Audience :: Developers
Classifier: Operating System :: OS Independent
